{
  "$metadata": {
    "generator": "designlang",
    "version": "7.0.0",
    "spec": "https://design-tokens.github.io/community-group/format/",
    "source": "https://blog.n8n.io/n8n-mcp-server/",
    "generatedAt": "2026-05-06T09:50:54.541Z"
  },
  "primitive": {
    "color": {
      "brand": {
        "primary": {
          "$value": "#ee4f27",
          "$type": "color"
        },
        "secondary": {
          "$value": "#1f192a",
          "$type": "color"
        }
      },
      "neutral": {
        "n100": {
          "$value": "#ffffff",
          "$type": "color"
        },
        "n200": {
          "$value": "#6f6f6f",
          "$type": "color"
        },
        "n300": {
          "$value": "#c4bbd3",
          "$type": "color"
        },
        "n400": {
          "$value": "#e4e4e4",
          "$type": "color"
        },
        "n500": {
          "$value": "#000000",
          "$type": "color"
        },
        "n600": {
          "$value": "#4b4b4b",
          "$type": "color"
        },
        "n700": {
          "$value": "#6b7280",
          "$type": "color"
        },
        "n800": {
          "$value": "#f5f5f5",
          "$type": "color"
        },
        "n900": {
          "$value": "#545454",
          "$type": "color"
        },
        "n1000": {
          "$value": "#c1c1c1",
          "$type": "color"
        }
      },
      "background": {
        "bg0": {
          "$value": "#0e0918",
          "$type": "color"
        },
        "bg1": {
          "$value": "#000000",
          "$type": "color"
        },
        "bg2": {
          "$value": "#ffffff",
          "$type": "color"
        },
        "bg3": {
          "$value": "#21ace8",
          "$type": "color"
        },
        "bg4": {
          "$value": "#1b1728",
          "$type": "color"
        },
        "bg5": {
          "$value": "#fefefe",
          "$type": "color"
        }
      },
      "text": {
        "text0": {
          "$value": "#000000",
          "$type": "color"
        },
        "text1": {
          "$value": "#ffffff",
          "$type": "color"
        },
        "text2": {
          "$value": "#c4bbd3",
          "$type": "color"
        },
        "text3": {
          "$value": "#6b7280",
          "$type": "color"
        },
        "text4": {
          "$value": "#e4e4e4",
          "$type": "color"
        },
        "text5": {
          "$value": "#1e1e1e",
          "$type": "color"
        },
        "text6": {
          "$value": "#545454",
          "$type": "color"
        },
        "text7": {
          "$value": "#1b1728",
          "$type": "color"
        },
        "text8": {
          "$value": "#ee4f27",
          "$type": "color"
        },
        "text9": {
          "$value": "#fefefe",
          "$type": "color"
        }
      }
    },
    "spacing": {
      "s0": {
        "$value": "1px",
        "$type": "dimension"
      },
      "s1": {
        "$value": "14px",
        "$type": "dimension"
      },
      "s2": {
        "$value": "24px",
        "$type": "dimension"
      },
      "s3": {
        "$value": "28px",
        "$type": "dimension"
      },
      "s4": {
        "$value": "32px",
        "$type": "dimension"
      },
      "s5": {
        "$value": "44px",
        "$type": "dimension"
      },
      "s6": {
        "$value": "48px",
        "$type": "dimension"
      },
      "s7": {
        "$value": "50px",
        "$type": "dimension"
      },
      "s8": {
        "$value": "60px",
        "$type": "dimension"
      },
      "s9": {
        "$value": "64px",
        "$type": "dimension"
      },
      "s10": {
        "$value": "105px",
        "$type": "dimension"
      },
      "s11": {
        "$value": "140px",
        "$type": "dimension"
      },
      "s12": {
        "$value": "160px",
        "$type": "dimension"
      },
      "s13": {
        "$value": "396px",
        "$type": "dimension"
      }
    },
    "radius": {
      "r0": {
        "$value": "2px",
        "$type": "dimension"
      },
      "r1": {
        "$value": "7px",
        "$type": "dimension"
      },
      "r2": {
        "$value": "16px",
        "$type": "dimension"
      },
      "r3": {
        "$value": "1057px",
        "$type": "dimension"
      }
    },
    "shadow": {
      "sh0": {
        "$value": "rgba(255, 255, 255, 0.19) 0px 0px 1.802px 0px, rgba(255, 255, 255, 0.1) 0px 0.451px 0px 0.901px inset",
        "$type": "shadow"
      },
      "sh1": {
        "$value": "rgba(0, 0, 0, 0.35) 1px 2px 8px 0px",
        "$type": "shadow"
      },
      "sh2": {
        "$value": "rgba(0, 0, 0, 0.15) 0px 4px 12px 0px",
        "$type": "shadow"
      }
    },
    "fontFamily": {
      "f0": {
        "$value": "Geomanist",
        "$type": "fontFamily"
      },
      "f1": {
        "$value": "Open Sans",
        "$type": "fontFamily"
      },
      "f2": {
        "$value": "Times New Roman",
        "$type": "fontFamily"
      },
      "f3": {
        "$value": "Arial",
        "$type": "fontFamily"
      },
      "f4": {
        "$value": "SF Mono",
        "$type": "fontFamily"
      }
    }
  },
  "semantic": {
    "color": {
      "action": {
        "primary": {
          "$value": "{primitive.color.brand.primary}",
          "$type": "color"
        },
        "secondary": {
          "$value": "{primitive.color.brand.secondary}",
          "$type": "color"
        }
      },
      "surface": {
        "default": {
          "$value": "{primitive.color.background.bg0}",
          "$type": "color"
        }
      },
      "text": {
        "body": {
          "$value": "{primitive.color.text.text0}",
          "$type": "color"
        }
      }
    },
    "typography": {
      "body": {
        "$value": {
          "fontFamily": "Geomanist",
          "fontSize": "38px",
          "fontWeight": "400",
          "lineHeight": "41.8px"
        },
        "$type": "typography"
      }
    },
    "radius": {
      "control": {
        "$value": "{primitive.radius.r0}",
        "$type": "dimension"
      }
    },
    "shadow": {
      "elevated": {
        "$value": "{primitive.shadow.sh0}",
        "$type": "shadow"
      }
    }
  }
}